Metadata-Version: 2.1
Name: gendocs
Version: 0.3.1
Summary: Automatic documentation pages generation
Home-page: https://github.com/banesullivan/gendocs
Author: Bane Sullivan
Author-email: banesullivan@gmail.com
License: UNKNOWN
Platform: UNKNOWN
Classifier: Programming Language :: Python
Classifier: License :: OSI Approved :: BSD License
Classifier: Operating System :: OS Independent
Classifier: Natural Language :: English
